normaldistrib.py
normaldistrib-1.0.0.dist-info/METADATA
normaldistrib-1.0.0.dist-info/WHEEL
normaldistrib-1.0.0.dist-info/top_level.txt
normaldistrib-1.0.0.dist-info/RECORD
