Metadata-Version: 2.1
Name: normaldistrib
Version: 1.0.0
Summary: Generate symmetric and asymmetric normal distributions
Author-email: "Pablo A. Kler" <kler@cimec.unl.edu.ar>, "Gabriel S. Gerlero" <ggerlero@cimec.unl.edu.ar>
Project-URL: Homepage, https://github.com/microfluidica/normaldistrib
Project-URL: Repository, https://github.com/microfluidica/normaldistrib
Classifier: Development Status :: 5 - Production/Stable
Classifier: Intended Audience :: Science/Research
Classifier: Intended Audience :: Developers
Classifier: License :: OSI Approved :: GNU General Public License v3 (GPLv3)
Classifier: Operating System :: OS Independent
Classifier: Programming Language :: Python :: 3 :: Only
Classifier: Programming Language :: Python :: 3.7
Classifier: Programming Language :: Python :: 3.8
Classifier: Programming Language :: Python :: 3.9
Classifier: Programming Language :: Python :: 3.10
Classifier: Programming Language :: Python :: 3.11
Classifier: Programming Language :: Python :: 3.12
Classifier: Programming Language :: Python :: 3.13
Classifier: Topic :: Scientific/Engineering :: Mathematics
Classifier: Topic :: Software Development
Requires-Python: >=3.7
Requires-Dist: numpy <3,>=1
Requires-Dist: scipy <2,>=1
Requires-Dist: numpy <3,>=1.25.0 ; python_version >= "3.11"
Provides-Extra: dev
Requires-Dist: normaldistrib[lint] ; extra == 'dev'
Provides-Extra: lint
Requires-Dist: ruff ; extra == 'lint'
